{
  "users": [
    {
      "id": "92fde87e-1f9d-467d-b89c-8c98fb583692",
      "name": "Jules Test",
      "email": "jules@gmail.com",
      "password": "password123",
      "usernames": [
        {
          "id": "83b70faa-4742-43cf-9202-3db7b7dcfcbf",
          "value": "julestest",
          "createdAt": 1772196159001,
          "updatedAt": 1772196159001
        }
      ],
      "usernameChangeLogs": [],
      "activeUsernameId": "83b70faa-4742-43cf-9202-3db7b7dcfcbf",
      "profilePic": "",
      "bio": "Updated Bio by Jules",
      "profession": "",
      "location": "",
      "socialLinks": {
        "twitter": "",
        "linkedin": "",
        "github": ""
      },
      "stats": {
        "posts": 0,
        "followers": 0,
        "following": 0
      },
      "isPrivate": false
    },
    {
      "id": "9e8df6f6-865b-428d-a03a-3d3548a34da4",
      "name": "Jules Test",
      "email": "jules_d8634fbb@gmail.com",
      "password": "password123",
      "usernames": [
        {
          "id": "25b3b446-ca3b-4863-ba43-0fcc94a819dc",
          "value": "jules_d8634fbb",
          "createdAt": 1772196223146,
          "updatedAt": 1772196223146
        }
      ],
      "usernameChangeLogs": [],
      "activeUsernameId": "25b3b446-ca3b-4863-ba43-0fcc94a819dc",
      "profilePic": "",
      "bio": "Updated Bio by Jules",
      "profession": "",
      "location": "",
      "socialLinks": {
        "twitter": "",
        "linkedin": "",
        "github": ""
      },
      "stats": {
        "posts": 2,
        "followers": 0,
        "following": 0
      },
      "isPrivate": false
    },
    {
      "id": "942df308-aed9-4a81-9b79-63e979433130",
      "name": "Jules Test",
      "email": "jules_2e406383@gmail.com",
      "password": "password123",
      "usernames": [
        {
          "id": "e89230ac-57f8-4647-a713-97c645044c93",
          "value": "jules_2e406383",
          "createdAt": 1772196244121,
          "updatedAt": 1772196244121
        }
      ],
      "usernameChangeLogs": [],
      "activeUsernameId": "e89230ac-57f8-4647-a713-97c645044c93",
      "profilePic": "",
      "bio": "Updated Bio by Jules",
      "profession": "",
      "location": "",
      "socialLinks": {
        "twitter": "",
        "linkedin": "",
        "github": ""
      },
      "stats": {
        "posts": 1,
        "followers": 0,
        "following": 0
      },
      "isPrivate": false
    },
    {
      "id": "9da8ded0-fb1b-4c45-8169-34a48750bbca",
      "name": "User A",
      "email": "usera@gmail.com",
      "password": "password123",
      "usernames": [
        {
          "id": "e49081b8-aa06-432d-bc70-1436631adc6e",
          "value": "usera",
          "createdAt": 1772214489382,
          "updatedAt": 1772214489382
        }
      ],
      "usernameChangeLogs": [],
      "activeUsernameId": "e49081b8-aa06-432d-bc70-1436631adc6e",
      "profilePic": "",
      "bio": "",
      "profession": "",
      "location": "",
      "socialLinks": {
        "twitter": "",
        "linkedin": "",
        "github": ""
      },
      "stats": {
        "posts": 0,
        "followers": 0,
        "following": 0
      },
      "isPrivate": false
    },
    {
      "id": "12e2e554-6d20-42fd-877b-a379d7c824ae",
      "name": "Test User",
      "email": "test1772214601@gmail.com",
      "password": "password123",
      "usernames": [
        {
          "id": "ba2f5db2-9509-4ae4-8296-a3c6f244276c",
          "value": "user1772214601",
          "createdAt": 1772214602244,
          "updatedAt": 1772214602244
        }
      ],
      "usernameChangeLogs": [],
      "activeUsernameId": "ba2f5db2-9509-4ae4-8296-a3c6f244276c",
      "profilePic": "",
      "bio": "",
      "profession": "",
      "location": "",
      "socialLinks": {
        "twitter": "",
        "linkedin": "",
        "github": ""
      },
      "stats": {
        "posts": 0,
        "followers": 0,
        "following": 0
      },
      "isPrivate": false
    },
    {
      "id": "98121807-022d-47f8-a5bd-bc8b4c102784",
      "name": "User Alpha",
      "email": "alpha@gmail.com",
      "password": "password123",
      "usernames": [
        {
          "id": "416c2e81-dd53-4fdb-8b94-49eab38320f0",
          "value": "useralpha",
          "createdAt": 1772214689574,
          "updatedAt": 1772214689574
        }
      ],
      "usernameChangeLogs": [],
      "activeUsernameId": "416c2e81-dd53-4fdb-8b94-49eab38320f0",
      "profilePic": "",
      "bio": "",
      "profession": "",
      "location": "",
      "socialLinks": {
        "twitter": "",
        "linkedin": "",
        "github": ""
      },
      "stats": {
        "posts": 0,
        "followers": 0,
        "following": 0
      },
      "isPrivate": false
    },
    {
      "id": "6c4820b1-a710-43b4-b7a9-6178c9310533",
      "name": "User Beta",
      "email": "beta@gmail.com",
      "password": "password123",
      "usernames": [
        {
          "id": "bdef2b8e-0704-4d3a-8100-c56683d47fea",
          "value": "userbeta",
          "createdAt": 1772214690741,
          "updatedAt": 1772214690741
        }
      ],
      "usernameChangeLogs": [],
      "activeUsernameId": "bdef2b8e-0704-4d3a-8100-c56683d47fea",
      "profilePic": "",
      "bio": "",
      "profession": "",
      "location": "",
      "socialLinks": {
        "twitter": "",
        "linkedin": "",
        "github": ""
      },
      "stats": {
        "posts": 0,
        "followers": 1,
        "following": 0
      },
      "isPrivate": false
    },
    {
      "id": "0d2b58c0-30aa-451c-bea2-1c48f0b086fd",
      "name": "User 1",
      "email": "u1@gmail.com",
      "password": "password123",
      "usernames": [],
      "usernameChangeLogs": [],
      "activeUsernameId": null,
      "profilePic": "",
      "bio": "",
      "profession": "",
      "location": "",
      "socialLinks": {
        "twitter": "",
        "linkedin": "",
        "github": ""
      },
      "stats": {
        "posts": 0,
        "followers": 0,
        "following": 1
      },
      "isPrivate": false
    },
    {
      "id": "a79d0803-2ced-4196-bd05-f0cc70e47021",
      "name": "User 2",
      "email": "u2@gmail.com",
      "password": "password123",
      "usernames": [],
      "usernameChangeLogs": [],
      "activeUsernameId": null,
      "profilePic": "",
      "bio": "",
      "profession": "",
      "location": "",
      "socialLinks": {
        "twitter": "",
        "linkedin": "",
        "github": ""
      },
      "stats": {
        "posts": 0,
        "followers": 1,
        "following": 0
      },
      "isPrivate": false
    },
    {
      "id": "39b54127-00e6-4218-9b47-dcf929d6de6c",
      "name": "User PC",
      "email": "pc@gmail.com",
      "password": "password123",
      "usernames": [
        {
          "id": "4768675b-f927-435a-b98c-af7e54742b1a",
          "value": "userpc",
          "createdAt": 1772216385803,
          "updatedAt": 1772216385803
        }
      ],
      "usernameChangeLogs": [],
      "activeUsernameId": "4768675b-f927-435a-b98c-af7e54742b1a",
      "profilePic": "",
      "bio": "",
      "profession": "",
      "location": "",
      "socialLinks": {
        "twitter": "",
        "linkedin": "",
        "github": ""
      },
      "stats": {
        "posts": 0,
        "followers": 0,
        "following": 0
      },
      "isPrivate": false
    },
    {
      "id": "d714ba50-5ba8-4ebc-8e1d-adcfce30f412",
      "name": "User PC",
      "email": "pc_1772216599@gmail.com",
      "password": "password123",
      "usernames": [
        {
          "id": "d5022002-878f-42c2-8559-b9a055d7c069",
          "value": "userpc_1772216600",
          "createdAt": 1772216600704,
          "updatedAt": 1772216600704
        }
      ],
      "usernameChangeLogs": [],
      "activeUsernameId": "d5022002-878f-42c2-8559-b9a055d7c069",
      "profilePic": "",
      "bio": "Updated Bio on PC",
      "profession": "",
      "location": "",
      "socialLinks": {
        "twitter": "",
        "linkedin": "",
        "github": ""
      },
      "stats": {
        "posts": 0,
        "followers": 0,
        "following": 0
      },
      "isPrivate": false
    },
    {
      "id": "1a10fbde-e0c1-409c-9c0a-0c3b6b51073f",
      "name": "User PC",
      "email": "pc_1772216655@gmail.com",
      "password": "password123",
      "usernames": [
        {
          "id": "728e1bc1-fbe3-42e2-9905-54fb926ee378",
          "value": "userpc_1772216656",
          "createdAt": 1772216656701,
          "updatedAt": 1772216656701
        }
      ],
      "usernameChangeLogs": [],
      "activeUsernameId": "728e1bc1-fbe3-42e2-9905-54fb926ee378",
      "profilePic": "",
      "bio": "Updated Bio on PC",
      "profession": "",
      "location": "",
      "socialLinks": {
        "twitter": "",
        "linkedin": "",
        "github": ""
      },
      "stats": {
        "posts": 0,
        "followers": 0,
        "following": 0
      },
      "isPrivate": false
    },
    {
      "id": "22f63027-1b63-43f0-8c05-27430bf3b876",
      "name": "Alpha",
      "email": "a_1772216687@gmail.com",
      "password": "password123",
      "usernames": [
        {
          "id": "4b2d8952-35b3-46d5-9574-424ae7b2555b",
          "value": "alpha_1772216688",
          "createdAt": 1772216688749,
          "updatedAt": 1772216688749
        }
      ],
      "usernameChangeLogs": [],
      "activeUsernameId": "4b2d8952-35b3-46d5-9574-424ae7b2555b",
      "profilePic": "",
      "bio": "",
      "profession": "",
      "location": "",
      "socialLinks": {
        "twitter": "",
        "linkedin": "",
        "github": ""
      },
      "stats": {
        "posts": 0,
        "followers": 0,
        "following": 1
      },
      "isPrivate": false
    },
    {
      "id": "1c7ca2f4-e7ef-490b-8500-157964eaf88d",
      "name": "Beta",
      "email": "b_1772216688@gmail.com",
      "password": "password123",
      "usernames": [
        {
          "id": "7aef5b5f-3fa9-421e-829f-e84d0982fae3",
          "value": "beta_1772216689",
          "createdAt": 1772216689883,
          "updatedAt": 1772216689883
        }
      ],
      "usernameChangeLogs": [],
      "activeUsernameId": "7aef5b5f-3fa9-421e-829f-e84d0982fae3",
      "profilePic": "",
      "bio": "",
      "profession": "",
      "location": "",
      "socialLinks": {
        "twitter": "",
        "linkedin": "",
        "github": ""
      },
      "stats": {
        "posts": 0,
        "followers": 0,
        "following": 0
      },
      "isPrivate": false
    },
    {
      "id": "74e49b97-4a3b-42d1-a578-dc41c242e763",
      "name": "Test User",
      "email": "testuser@gmail.com",
      "password": "password123",
      "usernames": [
        {
          "id": "eea40ae9-35b6-4bc7-9643-18652c14bf3f",
          "value": "testuser",
          "createdAt": 1772267936380,
          "updatedAt": 1772267936380
        }
      ],
      "usernameChangeLogs": [],
      "activeUsernameId": "eea40ae9-35b6-4bc7-9643-18652c14bf3f",
      "profilePic": "",
      "bio": "",
      "profession": "",
      "location": "",
      "socialLinks": {
        "twitter": "",
        "linkedin": "",
        "github": ""
      },
      "stats": {
        "posts": 0,
        "followers": 0,
        "following": 0
      },
      "isPrivate": false
    },
    {
      "id": "49aa5ef9-400c-4e63-8e4c-b3798c5e07c8",
      "name": "Verify User",
      "email": "verify@gmail.com",
      "password": "password123",
      "usernames": [],
      "usernameChangeLogs": [],
      "activeUsernameId": null,
      "profilePic": "",
      "bio": "",
      "profession": "",
      "location": "",
      "socialLinks": {
        "twitter": "",
        "linkedin": "",
        "github": ""
      },
      "stats": {
        "posts": 0,
        "followers": 0,
        "following": 0
      },
      "isPrivate": false
    },
    {
      "id": "858237d5-c8fa-4fa5-bc73-469fed248345",
      "name": "Test User",
      "email": "test@gmail.com",
      "password": "strongpassword123",
      "usernames": [
        {
          "id": "a6accb24-03e0-486c-8b0c-20a36a6ebe14",
          "value": "testuser1772276123",
          "createdAt": 1772276123439,
          "updatedAt": 1772276123439
        }
      ],
      "usernameChangeLogs": [],
      "activeUsernameId": "a6accb24-03e0-486c-8b0c-20a36a6ebe14",
      "profilePic": "",
      "bio": "",
      "profession": "",
      "location": "",
      "socialLinks": {
        "twitter": "",
        "linkedin": "",
        "github": ""
      },
      "stats": {
        "posts": 0,
        "followers": 0,
        "following": 0
      },
      "isPrivate": false
    }
  ],
  "posts": [
    {
      "id": "9d8a709a-0b0e-4ddb-8d47-2a63d071c2c8",
      "userId": "942df308-aed9-4a81-9b79-63e979433130",
      "userName": "jules_2e406383",
      "type": "carousel",
      "caption": "Verification Post",
      "description": "Verification Description",
      "files": [
        {
          "name": "dummy_2e406383.png",
          "type": "image/png",
          "size": 67,
          "dataUrl": "data:image/png;base64,iVBORw0KGgoAAAANSUhEUgAAAAEAAAABCAYAAAAfFcSJAAAACklEQVR4nGMAAQAABQABDQottAAAAABJRU5ErkJggg=="
        }
      ],
      "edits": [
        {
          "name": "dummy_2e406383.png",
          "trimStart": 0,
          "trimEnd": 0,
          "overlayText": "",
          "overlayColor": "#ffffff",
          "overlayX": 10,
          "overlayY": 10
        }
      ],
      "createdAt": "2026-02-27T12:44:05.711Z",
      "expiresAt": null,
      "interactions": {
        "likes": 0,
        "likedBy": [],
        "comments": [],
        "shares": 0
      }
    },
    {
      "id": "649b7993-c3b4-48ab-ac20-5a87148ba0db",
      "userId": "9e8df6f6-865b-428d-a03a-3d3548a34da4",
      "userName": "jules_d8634fbb",
      "type": "carousel",
      "caption": "Binary Storage Verification",
      "description": "",
      "files": [
        {
          "name": "storage_test.png",
          "type": "image/png",
          "size": 67,
          "dataUrl": "/uploads/5ea1355e-2925-479f-aeb4-ccd1828f49ff.png"
        }
      ],
      "edits": [
        {
          "name": "storage_test.png",
          "trimStart": 0,
          "trimEnd": 0,
          "overlayText": "",
          "overlayColor": "#ffffff",
          "overlayX": 10,
          "overlayY": 10
        }
      ],
      "createdAt": "2026-02-27T14:22:10.277Z",
      "expiresAt": null,
      "interactions": {
        "likes": 0,
        "likedBy": [],
        "comments": [],
        "shares": 0
      }
    },
    {
      "id": "2d4676ca-54fd-4ee2-8062-ce7f3737acf3",
      "userId": "9e8df6f6-865b-428d-a03a-3d3548a34da4",
      "userName": "jules_d8634fbb",
      "type": "carousel",
      "caption": "Binary Storage Verification",
      "description": "",
      "files": [
        {
          "name": "storage_test.png",
          "type": "image/png",
          "size": 67,
          "dataUrl": "/uploads/e3f1f904-f169-4fa0-b476-d047675527b6.png"
        }
      ],
      "edits": [
        {
          "name": "storage_test.png",
          "trimStart": 0,
          "trimEnd": 0,
          "overlayText": "",
          "overlayColor": "#ffffff",
          "overlayX": 10,
          "overlayY": 10
        }
      ],
      "createdAt": "2026-02-27T14:24:29.085Z",
      "expiresAt": null,
      "interactions": {
        "likes": 0,
        "likedBy": [],
        "comments": [],
        "shares": 0
      }
    }
  ],
  "relationships": [
    {
      "id": "818a7317-d94c-4d1d-8d69-5789862a1352",
      "followerId": "0d2b58c0-30aa-451c-bea2-1c48f0b086fd",
      "followingId": "a79d0803-2ced-4196-bd05-f0cc70e47021",
      "status": "accepted"
    },
    {
      "id": "f8eec8bb-da2e-408b-b627-3861e4ca60f3",
      "followerId": "22f63027-1b63-43f0-8c05-27430bf3b876",
      "followingId": "6c4820b1-a710-43b4-b7a9-6178c9310533",
      "status": "accepted"
    }
  ],
  "messages": [
    {
      "id": "d3f38b31-955a-4386-8ac9-4f5a00bec6de",
      "chatId": "dm:a79d0803-2ced-4196-bd05-f0cc70e47021",
      "senderId": "0d2b58c0-30aa-451c-bea2-1c48f0b086fd",
      "text": "Hi",
      "participants": [
        "0d2b58c0-30aa-451c-bea2-1c48f0b086fd",
        "a79d0803-2ced-4196-bd05-f0cc70e47021"
      ]
    },
    {
      "id": "ec42cfdf-f21b-40e7-b27a-0f42b2cbc2c7",
      "chatId": "dm:a79d0803-2ced-4196-bd05-f0cc70e47021",
      "senderId": "0d2b58c0-30aa-451c-bea2-1c48f0b086fd",
      "text": "Hi again",
      "participants": [
        "0d2b58c0-30aa-451c-bea2-1c48f0b086fd",
        "a79d0803-2ced-4196-bd05-f0cc70e47021"
      ],
      "reactions": [
        {
          "userId": "a79d0803-2ced-4196-bd05-f0cc70e47021",
          "emoji": "❤️"
        }
      ]
    }
  ]
}